awesome_django_timezones/__init__.py
awesome_django_timezones/apps.py
awesome_django_timezones/middleware.py
awesome_django_timezones/static/js/awesome_django_timezones.js
awesome_django_timezones-0.3.0.dist-info/AUTHORS.rst
awesome_django_timezones-0.3.0.dist-info/LICENSE
awesome_django_timezones-0.3.0.dist-info/METADATA
awesome_django_timezones-0.3.0.dist-info/WHEEL
awesome_django_timezones-0.3.0.dist-info/top_level.txt
awesome_django_timezones-0.3.0.dist-info/RECORD
