Metadata-Version: 2.1
Name: awesome-django-timezones
Version: 0.3.0
Summary: Easily set a localized timezone for users
Home-page: https://github.com/wgordon17/awesome-django-timezones
Author: Will Gordon
Author-email: will@gordoncode.com
License: MIT
Project-URL: Documentation, https://awesome-django-timezones.readthedocs.io
Project-URL: Source, https://github.com/wgordon17/awesome-django-timezones
Keywords: awesome-django-timezones
Platform: UNKNOWN
Classifier: Intended Audience :: Developers
Classifier: License :: OSI Approved :: MIT License
Classifier: Natural Language :: English
Classifier: Programming Language :: Python :: 3
Classifier: Programming Language :: Python :: 3.6
Classifier: Programming Language :: Python :: 3 :: Only
Classifier: Programming Language :: Python :: Implementation :: CPython
